DeepFuseNMF/Batcheffect_precorrection.py
DeepFuseNMF/__init__.py
DeepFuseNMF/train.py
DeepFuseNMF/data/__init__.py
DeepFuseNMF/data/data_util.py
DeepFuseNMF/data/dataset.py
DeepFuseNMF/model/__init__.py
DeepFuseNMF/model/models.py
DeepFuseNMF/model/models2.py
DeepFuseNMF/model/models3.py
DeepFuseNMF/utils/__init__.py
DeepFuseNMF/utils/utils.py
DeepFuseNMF/utils/visualize.py
DeepFuseNMF-0.2.0.dist-info/LICENSE
DeepFuseNMF-0.2.0.dist-info/METADATA
DeepFuseNMF-0.2.0.dist-info/WHEEL
DeepFuseNMF-0.2.0.dist-info/top_level.txt
DeepFuseNMF-0.2.0.dist-info/RECORD
