Metadata-Version: 2.1
Name: DeepFuseNMF
Version: 0.2.0
Summary: Interpretable super-resolution dimension reduction of spatial transcriptomics data by DeepFuseNMF
Author: Junjie Tang, Kun Qian
Author-email: junjie.tang@pku.edu.cn, kunqian@stu.pku.edu.cn
Maintainer: Kun Qian
Maintainer-email: kunqian@stu.pku.edu.cn
License: MIT Licence
Requires-Python: >=3.9
License-File: LICENSE
Requires-Dist: numpy >=1.21.2
Requires-Dist: cython >=0.29.24
Requires-Dist: torch >=1.7.0
Requires-Dist: scikit-learn >=0.23.2
Requires-Dist: matplotlib
Requires-Dist: scikit-learn
Requires-Dist: tqdm
Requires-Dist: h5py
Requires-Dist: scanpy
Requires-Dist: pandas
Requires-Dist: scikit-image
Requires-Dist: opencv-python
Requires-Dist: scipy
